{
  "newsletter": {
    "date": "2025-12-19",
    "cover_image": "https://f4.bcbits.com/img/a0652868742_5.jpg",
    "agenda": [
      {
        "event": "Concert de Tristwch Y Fenywod",
        "location": "Lyon, Le Périscope",
        "date": "2025-12-22",
        "description": "Tristwch Y Fenywod, groupe de gothic avant-rock, sera en concert au Périscope à Lyon. Un voyage onirique entre Pornography des Cure et Dead Can Dance."
      },
      {
        "event": "Concert de Saint Abdullah & Eomac, Deep Triskell, Maoupa Mazzocchetti",
        "location": "Lyon, Le Périscope et Le Sonic",
        "date": "2025-12-21",
        "description": "Soirée en deux temps et en circulation entre Le Périscope et Le Sonic avec des concerts et un club."
      },
      {
        "event": "Soirée Modestine, Allball, DJ Molo & Calmos",
        "location": "Aux Ardufs",
        "date": "2025-12-21",
        "description": "Soirée avec Modestine (légume-pop décharnée), Allball (sasquatch-rock contemplatif), et DJ Molo & Calmos."
      },
      {
        "event": "Concert de Feu! Catherine & Paula Poney, 1000 et 3 Loutres",
        "location": "Raminagrobis",
        "date": "2025-12-12",
        "description": "Concert à 19h30 avec Feu! Catherine & Paula Poney et 1000 et 3 Loutres."
      },
      {
        "event": "Concert de Mash Is A Girl, Jean-Luc Guionnet",
        "location": "Le 17",
        "date": "2025-12-09",
        "description": "Concert de Mash Is A Girl et Jean-Luc Guionnet au 17."
      },
      {
        "event": "Concert de Tropacabana, Philippe Lavigne et son orchestre",
        "location": "Lyon",
        "date": "2025-12-11",
        "description": "Concert avec Tropacabana et Philippe Lavigne et son orchestre."
      }
    ],
    "members": [
      {
        "name": "mbertier",
        "discoveries": [
          {
            "title": "Soft Selection 84 - A Nippon DIY Wave compilation by GLOSSY MISTAKES",
            "description": "Réédition d'une compilation new wave japonaise des années 1980, originellement publiée sur le label DIY Soft. Une capsule temporelle de créativité éclectique.",
            "link": "https://www.musiques-incongrues.net/d/15362-soft-selection-84-a-nippon-diy-wave-compilation-by-glossy-mistakes/1"
          },
          {
            "title": "03092023 by boredofcanada",
            "description": "Mini-album bruitiste réalisé avec des fichiers ROM de jeux vidéo et une vidéo mp4 importée dans Audacity et modifiée aléatoirement.",
            "link": "https://www.musiques-incongrues.net/d/15361-03092023-by-boredofcanada/1"
          },
          {
            "title": "Second Hand Banger by Tongue Bundle",
            "description": "Compilation de Tongue Bundle, avec des morceaux inédits et des rééditions de divers albums.",
            "link": "https://www.musiques-incongrues.net/d/15359-second-hand-banger-by-tongue-bundle/1"
          },
          {
            "title": "3.5.2025 by Acid Granny",
            "description": "Nouvel album d'Acid Granny, enregistré en live près du pont O'Connell en mai 2025.",
            "link": "https://www.musiques-incongrues.net/d/15358-352025-by-acid-granny/1"
          },
          {
            "title": "The Ghost Office by Colin Potter",
            "description": "Album de Colin Potter, avec des morceaux qui formaient l'édition double LP étendue publiée par Deep Distance en 2017.",
            "link": "https://www.musiques-incongrues.net/d/15357-the-ghost-office-by-colin-potter/1"
          },
          {
            "title": "An Irish Almanac of Noise and Experimental Music From 2025 by Nyahh Records",
            "description": "Collection de musiciens expérimentaux contemporains de toute l'île d'Irlande, avec des œuvres couvrant le bruit, l'acoustique, l'électroacoustique, l'électronique, la musique concrète, la musique sur bande et le drone.",
            "link": "https://www.musiques-incongrues.net/d/15355-an-irish-almanac-of-noise-and-experimental-music-from-2025-by-nyahh-records/1"
          }
        ]
      },
      {
        "name": "oyibo",
        "discoveries": [
          {
            "title": "Pétale Défoule by La Bande à Bader",
            "description": "Album de La Bande à Bader, avec des influences de breakbeat, dnb, et une ambiance NewTrad.",
            "link": "https://www.musiques-incongrues.net/d/15351-petale-defoule-by-la-bande-a-bader/1"
          },
          {
            "title": "Ora Sono Un Lago by Bono / Burattini",
            "description": "Nouvel album de Bono / Burattini, enregistré et produit par l'ingénieur du son primé aux Grammy Awards, Francesco Donadello.",
            "link": "https://www.musiques-incongrues.net/d/15356-ora-sono-un-lago-by-bono-burattini/1"
          },
          {
            "title": "Dubcore Volume 26 by Gabber Dub Project",
            "description": "Nouvel EP de Gabber Dub Project, avec des morceaux puissants et des kicks lourds.",
            "link": "https://www.musiques-incongrues.net/d/15353-dubcore-volume-26-by-gabber-dub-project/1"
          }
        ]
      },
      {
        "name": "nota",
        "discoveries": [
          {
            "title": "The Land of Rising Fun",
            "description": "Émission radio Epsilonia sur Radio Libertaire, Paris.",
            "link": "https://www.musiques-incongrues.net/d/15339-the-land-of-rising-fun/1"
          },
          {
            "title": "Modestine, Allball, DJ Molo & Calmos",
            "description": "Soirée aux Ardufs avec Modestine (légume-pop décharnée), Allball (sasquatch-rock contemplatif), et DJ Molo & Calmos.",
            "link": "https://www.musiques-incongrues.net/d/15338-modestine-allball-dj-molo-calmos/1"
          },
          {
            "title": "Information Confidentielle de la Plus Haute Importance",
            "description": "Message mystérieux de notre agent à la Havane.",
            "link": "https://www.musiques-incongrues.net/d/15336-information-confidentielle-de-la-plus-haute-importance/1"
          }
        ]
      }
    ],
    "gallery": [
      {
        "url": "https://f4.bcbits.com/img/a0652868742_5.jpg",
        "description": "Image de l'album '2025.11.21' de CDR."
      }
    ],
    "markdown": "# Newsletter Musiques Incongrues - 19 Décembre 2025\n\n## Agenda\n\n### Concert de Tristwch Y Fenywod\n- **Lieu**: Lyon, Le Périscope\n- **Date**: 2025-12-22\n- **Description**: Tristwch Y Fenywod, groupe de gothic avant-rock, sera en concert au Périscope à Lyon. Un voyage onirique entre Pornography des Cure et Dead Can Dance.\n\n### Concert de Saint Abdullah & Eomac, Deep Triskell, Maoupa Mazzocchetti\n- **Lieu**: Lyon, Le Périscope et Le Sonic\n- **Date**: 2025-12-21\n- **Description**: Soirée en deux temps et en circulation entre Le Périscope et Le Sonic avec des concerts et un club.\n\n### Soirée Modestine, Allball, DJ Molo & Calmos\n- **Lieu**: Aux Ardufs\n- **Date**: 2025-12-21\n- **Description**: Soirée avec Modestine (légume-pop décharnée), Allball (sasquatch-rock contemplatif), et DJ Molo & Calmos.\n\n### Concert de Feu! Catherine & Paula Poney, 1000 et 3 Loutres\n- **Lieu**: Raminagrobis\n- **Date**: 2025-12-12\n- **Description**: Concert à 19h30 avec Feu! Catherine & Paula Poney et 1000 et 3 Loutres.\n\n### Concert de Mash Is A Girl, Jean-Luc Guionnet\n- **Lieu**: Le 17\n- **Date**: 2025-12-09\n- **Description**: Concert de Mash Is A Girl et Jean-Luc Guionnet au 17.\n\n### Concert de Tropacabana, Philippe Lavigne et son orchestre\n- **Lieu**: Lyon\n- **Date**: 2025-12-11\n- **Description**: Concert avec Tropacabana et Philippe Lavigne et son orchestre.\n\n\n## Découvertes des Membres\n\n### mbertier\n\n- **[Soft Selection 84 - A Nippon DIY Wave compilation by GLOSSY MISTAKES](https://www.musiques-incongrues.net/d/15362-soft-selection-84-a-nippon-diy-wave-compilation-by-glossy-mistakes/1)**\n  Réédition d'une compilation new wave japonaise des années 1980, originellement publiée sur le label DIY Soft. Une capsule temporelle de créativité éclectique.\n\n- **[03092023 by boredofcanada](https://www.musiques-incongrues.net/d/15361-03092023-by-boredofcanada/1)**\n  Mini-album bruitiste réalisé avec des fichiers ROM de jeux vidéo et une vidéo mp4 importée dans Audacity et modifiée aléatoirement.\n\n- **[Second Hand Banger by Tongue Bundle](https://www.musiques-incongrues.net/d/15359-second-hand-banger-by-tongue-bundle/1)**\n  Compilation de Tongue Bundle, avec des morceaux inédits et des rééditions de divers albums.\n\n- **[3.5.2025 by Acid Granny](https://www.musiques-incongrues.net/d/15358-352025-by-acid-granny/1)**\n  Nouvel album d'Acid Granny, enregistré en live près du pont O'Connell en mai 2025.\n\n- **[The Ghost Office by Colin Potter](https://www.musiques-incongrues.net/d/15357-the-ghost-office-by-colin-potter/1)**\n  Album de Colin Potter, avec des morceaux qui formaient l'édition double LP étendue publiée par Deep Distance en 2017.\n\n- **[An Irish Almanac of Noise and Experimental Music From 2025 by Nyahh Records](https://www.musiques-incongrues.net/d/15355-an-irish-almanac-of-noise-and-experimental-music-from-2025-by-nyahh-records/1)**\n  Collection de musiciens expérimentaux contemporains de toute l'île d'Irlande, avec des œuvres couvrant le bruit, l'acoustique, l'électroacoustique, l'électronique, la musique concrète, la musique sur bande et le drone.\n\n\n### oyibo\n\n- **[Pétale Défoule by La Bande à Bader](https://www.musiques-incongrues.net/d/15351-petale-defoule-by-la-bande-a-bader/1)**\n  Album de La Bande à Bader, avec des influences de breakbeat, dnb, et une ambiance NewTrad.\n\n- **[Ora Sono Un Lago by Bono / Burattini](https://www.musiques-incongrues.net/d/15356-ora-sono-un-lago-by-bono-burattini/1)**\n  Nouvel album de Bono / Burattini, enregistré et produit par l'ingénieur du son primé aux Grammy Awards, Francesco Donadello.\n\n- **[Dubcore Volume 26 by Gabber Dub Project](https://www.musiques-incongrues.net/d/15353-dubcore-volume-26-by-gabber-dub-project/1)**\n  Nouvel EP de Gabber Dub Project, avec des morceaux puissants et des kicks lourds.\n\n\n### nota\n\n- **[The Land of Rising Fun](https://www.musiques-incongrues.net/d/15339-the-land-of-rising-fun/1)**\n  Émission radio Epsilonia sur Radio Libertaire, Paris.\n\n- **[Modestine, Allball, DJ Molo & Calmos](https://www.musiques-incongrues.net/d/15338-modestine-allball-dj-molo-calmos/1)**\n  Soirée aux Ardufs avec Modestine (légume-pop décharnée), Allball (sasquatch-rock contemplatif), et DJ Molo & Calmos.\n\n- **[Information Confidentielle de la Plus Haute Importance](https://www.musiques-incongrues.net/d/15336-information-confidentielle-de-la-plus-haute-importance/1)**\n  Message mystérieux de notre agent à la Havane.\n\n\n## Galerie\n\n![Image de l'album '2025.11.21' de CDR](https://f4.bcbits.com/img/a0652868742_5.jpg)"
  }
}